LICENSE.txt
README.md
setup.py
linear_regression_mode.egg-info/PKG-INFO
linear_regression_mode.egg-info/SOURCES.txt
linear_regression_mode.egg-info/dependency_links.txt
linear_regression_mode.egg-info/requires.txt
linear_regression_mode.egg-info/top_level.txt
linear_regression_model/__init__.py
linear_regression_model/linear_regression.py