Metadata-Version: 2.1
Name: linear_regression_mode
Version: 1.0.0
Summary: An awesome package that does something
Home-page: http://pypi.python.org/pypi/<your_package_name>/
Author: Hakim
Author-email: af.maroc@esi-sba.dz
License: LICENSE.txt
License-File: LICENSE.txt
Requires-Dist: linear_regression_model
